speechmatics_flow/__init__.py
speechmatics_flow/cli.py
speechmatics_flow/cli_parser.py
speechmatics_flow/client.py
speechmatics_flow/exceptions.py
speechmatics_flow/models.py
speechmatics_flow/playback.py
speechmatics_flow/templates.py
speechmatics_flow/tool_function_param.py
speechmatics_flow/utils.py
speechmatics_flow-0.1.2.dist-info/licenses/LICENSE
speechmatics_flow-0.1.2.dist-info/METADATA
speechmatics_flow-0.1.2.dist-info/WHEEL
speechmatics_flow-0.1.2.dist-info/entry_points.txt
speechmatics_flow-0.1.2.dist-info/top_level.txt
speechmatics_flow-0.1.2.dist-info/RECORD
