Metadata-Version: 2.4
Name: speechmatics-flow
Version: 0.1.2
Summary: Python library and CLI for Speechmatics Flow API
Home-page: https://github.com/speechmatics/speechmatics-flow/
Author: Speechmatics
Author-email: support@speechmatics.com
License: MIT
Project-URL: Documentation, https://speechmatics.github.io/speechmatics-flow/
Project-URL: Source Code, https://github.com/speechmatics/speechmatics-flow/
Classifier: Environment :: Console
Classifier: Intended Audience :: Developers
Classifier: License :: OSI Approved :: MIT License
Classifier: Operating System :: OS Independent
Classifier: Programming Language :: Python :: 3
Classifier: Programming Language :: Python :: 3.10
Classifier: Topic :: Multimedia :: Sound/Audio :: Speech
Classifier: Topic :: Software Development :: Libraries :: Python Modules
Requires-Python: >=3.7
License-File: LICENSE
Requires-Dist: httpx==0.27.1
Requires-Dist: pyaudio==0.2.14
Requires-Dist: setuptools
Requires-Dist: websockets<=13.1,>=10
Requires-Dist: python-dotenv~=1.0
Dynamic: author
Dynamic: author-email
Dynamic: classifier
Dynamic: description
Dynamic: description-content-type
Dynamic: home-page
Dynamic: license
Dynamic: license-file
Dynamic: project-url
Dynamic: requires-dist
Dynamic: requires-python
Dynamic: summary
